setup.py
sortmuz/__init__.py
sortmuz/app.py
sortmuz.egg-info/PKG-INFO
sortmuz.egg-info/SOURCES.txt
sortmuz.egg-info/dependency_links.txt
sortmuz.egg-info/entry_points.txt
sortmuz.egg-info/requires.txt
sortmuz.egg-info/top_level.txt