Metadata-Version: 1.0
Name: sortmuz
Version: 0.2
Summary: sort downloaded music albums interactively
Home-page: https://github.com/eepp/sortmuz
Author: Philippe Proulx
Author-email: UNKNOWN
License: UNKNOWN
Keywords: sort music interactive
Platform: UNKNOWN
